TurtLSystems/__init__.py
TurtLSystems/examples.py
TurtLSystems/source.py
TurtLSystems-0.1.7.dist-info/LICENSE.txt
TurtLSystems-0.1.7.dist-info/METADATA
TurtLSystems-0.1.7.dist-info/WHEEL
TurtLSystems-0.1.7.dist-info/top_level.txt
TurtLSystems-0.1.7.dist-info/zip-safe
TurtLSystems-0.1.7.dist-info/RECORD
