Metadata-Version: 2.1
Name: TurtLSystems
Version: 0.1.7
Summary: Tool to draw L-systems via turtle graphics and save them as pngs and gifs.
Home-page: https://github.com/discretegames/TurtLSystems
Author: discretegames
Author-email: discretizedgames@gmail.com
License: MIT
Project-URL: GitHub, https://github.com/discretegames/TurtLSystems
Project-URL: PyPI, https://pypi.org/project/TurtLSystems
Project-URL: TestPyPi, https://test.pypi.org/project/TurtLSystems
Keywords: lindenmayer,system,lsystem,turtle,graphics,fractal,pattern,art,png,gif,animation,Sierpinski,Koch,Cantor,dragon
Platform: UNKNOWN
Classifier: Development Status :: 4 - Beta
Classifier: Intended Audience :: Education
Classifier: Intended Audience :: Science/Research
Classifier: Topic :: Artistic Software
Classifier: Topic :: Education
Classifier: Topic :: Multimedia :: Graphics
Classifier: Topic :: Multimedia :: Graphics :: Editors :: Vector-Based
Classifier: Topic :: Scientific/Engineering :: Mathematics
Classifier: Topic :: Scientific/Engineering :: Visualization
Classifier: Programming Language :: Python :: 3
Classifier: Programming Language :: Python :: 3.6
Classifier: Programming Language :: Python :: 3.7
Classifier: Programming Language :: Python :: 3.8
Classifier: Programming Language :: Python :: 3.9
Classifier: Programming Language :: Python :: 3.10
Classifier: License :: OSI Approved :: MIT License
Classifier: Typing :: Typed
License-File: LICENSE.txt
Requires-Dist: Pillow (>=6.2.0)
